Workbook

Sheet Assumptions
A1: Skills-Repo Outer Loop ROI Model · Assumptions
A2: Blue cells are editable inputs. All other cells are calculated. Scenarios tab shows side-by-side comparisons.
A4: Input (blue) — edit these | B4: Calculated | C4: Positive outcome | D4: Caution / check
A6: A · Fleet & Labour Context
A7: Engineering teams in fleet | B7: 50 | D7: Source: current Westpac NZ org chart
A8: Stories per team per month | B8: 8 | D8: Typical 2-week sprint velocity per team
A9: Stories through outer loop (%) | B9: 60 | D9: Not all stories need full outer loop — simple bug fixes, minor config changes excluded
A10: Blended rate — see Section B role rates below | B10: =AVERAGE(B15,B17,B19) -> 108.33333 | D10: Use loaded cost (salary + oncosts); NZD
A11: Overhead multiplier | B11: 1.35
A13: B · Conventional Story Prep Cost — Multi-Role Baseline (no pipeline)
A14: Role / Activity | B14: Hourly Rate (NZD) | C14: Hours per Story | D14: Notes
A15: BA / Product Analyst — discovery & benefit metric | B15: 85 | C15: 1.5 | D15: Writing problem statement, benefit metric, surface classification
A16: BA / Product Analyst — story & AC writing | B16: 85 | C16: 1 | D16: Drafting story description, acceptance criteria
A17: Tech Lead — architecture review & spike sizing | B17: 130 | C17: 1 | D17: Technical feasibility, dependency check, sizing
A18: Tech Lead — DoR gate review | B18: 130 | C18: 0.5 | D18: Reviewing AC completeness, test plan presence
A19: Product Owner — refinement facilitation | B19: 110 | C19: 0.75 | D19: Running the refinement meeting, decision-making
A20: Senior Eng #2 — refinement attendance | B20: 120 | C20: 0.5 | D20: Second senior eng pulled into refinement meeting
A21: BA — rework & clarification (post-refinement)
A22: Tech Lead — rework review | B22: 130 | C22: 0.25 | D22: Second pass after BA rework
A24: Overhead multiplier (oncosts, tooling, management) | B24: 1.35 | D24: Applies to all role costs; covers salary oncosts, tooling, management overhead
A25: Coordination overhead — scheduling, async Jira/Confluence (hrs) | B25: =AVERAGE(B15,B17,B19) -> 108.33333 | C25: 0.5 | D25: Calendar friction, Slack threads, waiting for reviews — not captured in meeting hours
A26: Quality inconsistency — downstream rework cost (hrs equiv) | B26: 120 | C26: 0.5 | D26: Variable quality across teams causes dev rework mid-sprint; priced at senior eng rate
A27: B · Conventional Story Prep Cost (Baseline — no pipeline)
A28: Total conventional hours per story (all roles + coordination) | B28: 1.5 | C28: =SUM(C15:C22)+C25+C26 -> 6.5 | D28: BA / product time for feature analysis, benefit articulation
A29: Conventional role cost per story (NZD) | B29: =SUMPRODUCT(B15:B22,C15:C22)*B24 -> 786.375 | D29: Sum of (rate × hours) for each role, multiplied by overhead
A30: Coordination overhead cost per story (NZD) | B30: =B25*C25*B24 -> 73.125
A31: Quality inconsistency cost per story (NZD) | B31: =B26*C26*B24 -> 81
A32: TOTAL conventional cost per story (NZD) | B32: =B29+B30+B31 -> 940.5
A33: Conventional cost per story (NZD) | B33: =B18*B10*B11 -> 19012.5
A35: C · Pipeline Token Cost (per story through outer loop)
A36: Discovery stage — Sonnet input tokens (k) | B36: 35 | D36: EXP-008 baseline: discovery stage context ~ 30–40k tokens in
A37: Discovery stage — Sonnet output tokens (k) | B37: 4
A38: Definition stage — Haiku input tokens (k) | B38: 20
A39: Definition stage — Haiku output tokens (k) | B39: 6
A40: Review / DoR stage — Haiku input tokens (k) | B40: 18
A41: Review / DoR stage — Haiku output tokens (k) | B41: 3
A42: Prompt cache hit rate (%) | B42: 70 | D42: Improves significantly at fleet scale as SKILL.md files stabilise
A43: Sonnet input price (USD per M tokens)
A44: Sonnet output price (USD per M tokens) | B44: 15
A45: Haiku input price (USD per M tokens) | B45: 1
A46: Haiku output price (USD per M tokens) | B46: 5
A47: Cache discount on input tokens (%) | B47: 90 | D47: Anthropic direct API only — not available via Copilot proxy path
A48: NZD/USD FX rate | B48: 1.62
A50: Effective Sonnet input cost/story (USD) | B50: =(B22/1000)*(B29*((1-B28/100)+B28/100*(1-B33/100))) -> -189.31487
A51: Sonnet output cost/story (USD) | B51: =(B23/1000)*B30 -> 0
A52: Haiku (definition+review) input cost/story (USD)
A53: Haiku output cost/story (USD) | B53: =((B25+B27)/1000)*B32 -> 101.8875
A54: Total pipeline token cost per story (USD) | B54: =B36+B37+B38+B39 -> 65
A55: Total pipeline token cost per story (NZD) | B55: =B40*B34 -> 0
A57: D · Human Time Saved by Pipeline
A58: Hours saved: discovery / analysis | B58: 1 | D58: Pipeline runs discovery skill; replaces BA draft time
A59: Hours saved: story writing | B59: 0.75
A60: Hours saved: DoR check & prep | B60: 0.5
A61: Hours saved: rework reduction | B61: 0.5
A62: Human oversight still required (hrs) | B62: 0.5 | D62: iwu.6 pattern: human-in-the-loop always required for SKILL.md tuning
A63: Net hours saved per story | B63: =SUM(B44:B47)-B48 -> 109.38
A64: Labour cost saved per story (NZD) | B64: =B49*AVERAGE(B15,B17)*B24 -> 0
A66: E · Net ROI per Story & Fleet Monthly
A67: Net saving per pipeline story (NZD) | B67: =B32*(B49/C28)-B41 -> -3 | C67: → Positive = pipeline pays back
A68: ROI multiple (saving / token cost) | B68: =IF(B41=0,"n/a",(B32*(B49/C28))/B41) -> 0
A69: Stories through pipeline per month (fleet) | B69: =B7*B8*(B9/100) -> 240
A70: Monthly fleet token spend (NZD) | B70: =B41*B55 -> 0
A71: Monthly fleet labour saving (NZD) | B71: =B32*(B49/C28)*B55 -> 0
A72: Monthly net fleet saving (NZD) | B72: =B57-B56 -> 0
A73: Annual net fleet saving (NZD) | B73: =B58*12 -> 12

Sheet Corpus Evidence
A1: Skills-Repo Outer Loop · Corpus Evidence · EXP-003 to EXP-009
A2: Measured artefact quality (AQ) and constraint propagation fidelity (CPF) from real pipeline runs across S2 (Lending Origination), S8 (Payments DR), S13 (Cross-border Remittance). AQ scored 0–1 by independent Sonnet judge. Human equivalent quality estimated by same rubric.
A4: 1 · Measured AQ & CPF by Configuration and Scenario (EXP-008 corpus)
A5: Configuration | B5: Model Routing | D5: S2 Lending Origination | F5: S8 Payments DR | H5: S13 Cross-Border Remittance
B6: Discovery | C6: Defn/Review/DoR | D6: CPF | E6: AQ | F6: CPF | G6: AQ | H6: CPF / AQ
A7: Config A (Sonnet baseline) | B7: Sonnet 4.6 | C7: Sonnet 4.6 | D7: 1 | E7: 0.9 | F7: 1 | G7: 0.8 | H7: 1.00 / 0.90
A8: Config B (Opus+Sonnet — conditional premium) | B8: Sonnet 4.6 | C8: Sonnet 4.6 | D8: 1 | E8: 0.9 | F8: 1 | G8: 1 | H8: 1.00 / ~0.90
A9: Config C (Sonnet disc + Haiku workers) | B9: Sonnet 4.6 | C9: Haiku 4.5 | D9: 1 | E9: 0.77 | F9: 1 | G9: 0.77 | H9: 1.00 / 0.77*
A10: Config D (GPT-4o) | B10: GPT-4o | C10: GPT-4o | D10: BLOCKED | E10: — | F10: BLOCKED | G10: — | H10: BLOCKED — schema drift
A11: * Config C AQ=0.77 average across S2/S8/S13. CPF=1.00 held — constraint propagation robust across all tested configs. Config B premium is scenario-conditional: manifests on S8 (system-enforceable gates) but not on S2/S13 (inherently human-process compliance).
A13: 2 · AQ Dimension Breakdown — Config A vs Config C (where they differ)
A14: AQ Dimension | B14: Config A (all Sonnet) | C14: Config C (Haiku workers) | D14: Delta | E14: Driver of gap
A15: Constraint completeness (AC covers all regulated constraints) | B15: 0.9 | C15: 0.8 | D15: 0.1 | E15: Haiku drops nuanced constraint detail in definition AC
A16: Story testability (AC unambiguous pass/fail for coding agent) | B16: 0.85 | C16: 0.75 | D16: 0.1 | E16: Haiku ACs more generic; harder to auto-verify
A17: DoR gate quality (named responsible party, deployment flags) | B17: 0.9 | C17: 0.75 | D17: 0.15 | E17: Haiku omits role-specific gate assignment more often
A18: Benefit metric alignment (story benefit traceable to feature metric) | B18: 0.88 | C18: 0.78 | D18: 0.1 | E18: Haiku less precise on benefit causality chain
A19: Regulatory surface coverage (RBNZ/CPG 220 obligations surfaced) | B19: 0.85 | C19: 0.75 | D19: 0.1 | E19: Haiku syntactically correct but misses semantic role of constraints
A21: 3 · Human Equivalent Quality Estimate (same AQ rubric applied to conventional process)
A22: Quality tier | B22: AQ range | C22: Process description | D22: CPF reliability | E22: Freq in fleet | F22: Equiv pipeline config
A23: Expert BA + senior tech lead (experienced regulated team) | B23: 0.80–0.90 | C23: Experienced BA writes full AC with constraint awareness; tech lead reviews for regulatory surface. Occurs when right people available. | D23: ~0.85 (manual, dependent on knowledge) | E23: ~20% of stories | F23: ≈ Config A
A24: Standard refinement (typical team maturity) | B24: 0.55–0.75 | C24: BA or PO writes story without deep regulatory context; tech lead adds some constraints in refinement. Most common pattern. | D24: ~0.55–0.65 (knowledge-dependent, variable) | E24: ~60% of stories | F24: ≈ Config C or below
A25: Rushed / understaffed (common in high-velocity teams) | B25: 0.30–0.55 | C25: Story written quickly, minimal review, DoR checked by tick-box. Constraints frequently missing or implicit. | D25: ~0.30–0.45 (high rework risk) | E25: ~20% of stories | F25: Below Config C
A26: WEIGHTED AVERAGE (fleet-realistic baseline) | B26: 0.57–0.72 | C26: Weighted by frequency: (0.20×0.85) + (0.60×0.65) + (0.20×0.42) = 0.65 midpoint | D26: ~0.60 weighted avg | E26: 100% | F26: Below Config C
A28: 4 · Cost vs Quality Comparison — Pipeline Configurations vs Human Baseline
A29: Option | B29: AQ (measured / est.) | C29: CPF reliability | D29: Est. token cost per story (NZD) | E29: Est. human labour cost per story (NZD) | F29: Total cost per story (NZD) | G29: Quality-adjusted cost index | H29: Notes
A30: Config A — all Sonnet (pipeline) | B30: 0.87 | C30: 1.00 (systematic) | D30: 2.5 | E30: 30 | F30: 32.5 | G30: 37 | H30: 30 = ~15min human oversight at $120/hr × 1.35 overhead. Token cost est. from EXP-008 token volumes.
A31: Config C — Sonnet disc + Haiku workers (current production routing) | B31: 0.77 | C31: 1.00 (systematic) | D31: 1.2 | E31: 30 | F31: 31.2 | G31: 41 | H31: Best cost-quality balance. EXP-003/008 validated. Recommended default.
A32: Config B — Opus+Sonnet (premium tier) | B32: 0.93 | C32: 1.00 (systematic) | D32: 6.5 | E32: 30 | F32: 36.5 | G32: 39 | H32: Premium justified for high-stakes regulated features only (S8-type). ~5x Config C token cost.
A33: Human — expert team (best-case conventional) | B33: 0.85 | C33: ~0.85 (manual) | D33: 0 | E33: 650 | F33: 650 | G33: 765 | H33: ~$650 = SUMPRODUCT of 8 roles from Assumptions sheet B. Best case — requires right people available.
A34: Human — standard refinement (fleet-realistic) | B34: 0.65 | C34: ~0.60 (variable) | D34: 0 | E34: 580 | F34: 580 | G34: 892 | H34: Slightly less time but lower quality output. Constraint gaps cause downstream rework not priced here.
A35: Human — rushed / understaffed | B35: 0.42 | C35: ~0.40 (high risk) | D35: 0 | E35: 420 | F35: 420 | G35: 1000 | H35: Less time but high rework cost downstream. CPF failures cause mid-sprint change requests.
A36: KEY INSIGHT: Config C (pipeline, current production) delivers AQ 0.77 at $31 NZD total cost per story vs $580 for fleet-realistic human baseline at AQ 0.65 — the pipeline produces HIGHER quality artefacts at 5% of the human cost. Quality-adjusted cost index: pipeline $40 vs human $892 per quality point.

Sheet Token Pricing Sensitivity
A1: Skills-Repo Outer Loop · Token Pricing Sensitivity · Post June 2026 Economics
A2: Compares pipeline cost under three harness paths: (1) Copilot per-token metering (no cache), (2) Direct Anthropic API with prompt cache, (3) Direct API + batch mode. ROI case tested against each. Human baseline unchanged.
A4: 1 · Token Volume Inputs — per story through full outer loop pipeline (Config C routing)
A5: Stage / model | B5: Input tokens (k) | C5: Output tokens (k) | D5: Notes
A6: Discovery — Sonnet 4.6 | B6: 35 | C6: 5 | D6: EXP-008 est. Largest stage; full feature context + constraints injected
A7: Definition — Haiku 4.5 (×2 stories) | B7: 20 | C7: 7 | D7: Config C routing. Two definition passes avg.
A8: Review — Haiku 4.5 | B8: 18 | C8: 3 | D8: Review stage; shorter output
A9: Test-plan — Haiku 4.5 | B9: 16 | C9: 5 | D9: Test case generation; moderate output
A10: Definition-of-Ready — Haiku 4.5 | B10: 12 | C10: 3 | D10: DoR gate check; structured pass/fail output
A11: TOTAL per story | B11: =SUM(B6:B10) -> 101 | C11: =SUM(C6:C10) -> 23
A13: 2 · Cost per Story — Three Harness / Pricing Paths
A14: Cost component | B14: Path 1 Copilot (no cache) | C14: Path 2 Direct API (with cache) | D14: Path 3 Direct API + Batch (50% off) | E14: Path 4 Copilot All-Sonnet (worst case) | F14: Notes
A16: Pricing assumptions (blue = editable)
A17: Sonnet input price (USD/M tokens) | B17: 3
A18: Sonnet output price (USD/M tokens) | B18: 15
A19: Haiku input price (USD/M tokens) | B19: 1
A20: Haiku output price (USD/M tokens) | B20: 5
A21: Prompt cache discount on input (%) | B21: 90 | C21: Anthropic direct API only — 90% saving on cached input tokens
A22: Cache hit rate — direct API (%) | B22: 70 | C22: Improves with fleet scale as SKILL.md stabilises
A23: Batch API discount (%) | B23: 50 | C23: Batch API: 50% discount, async 24hr SLA — viable for non-urgent pipeline runs
A24: NZD/USD FX rate | B24: 1.62
A25: Copilot cache availability | B25: None | C25: Copilot proxy does not expose prompt caching — full price on every token
A27: Calculated costs per story — by path
A28: Sonnet discovery — input cost (USD) | B28: =(B6/1000)*B17 -> 0.105 | C28: =(B6/1000)*(B17*((1-B22/100)+B22/100*(1-B21/100))) -> 0.03885 | D28: =(B6/1000)*(B17*((1-B22/100)+B22/100*(1-B21/100)))*((100-B23)/100) -> 0.019425 | E28: =(B6/1000)*B17 -> 0.105 | F28: Largest single cost item — discovery context is token-heavy
A29: Sonnet discovery — output cost (USD) | B29: =(C6/1000)*B18 -> 0.075 | C29: =(C6/1000)*B18 -> 0.075 | D29: =(C6/1000)*B18*((100-B23)/100) -> 0.0375 | E29: =(C6/1000)*B18 -> 0.075 | F29: Output not cached — full price on all paths
A30: Haiku workers — input cost (USD) | B30: =((B7+B8+B9+B10)/1000)*B17 -> 0.198 | C30: =((B7+B8+B9+B10)/1000)*(B19*((1-B22/100)+B22/100*(1-B21/100))) -> 0.02442 | D30: =((B7+B8+B9+B10)/1000)*(B19*((1-B22/100)+B22/100*(1-B21/100)))*((100-B23)/100) -> 0.01221 | E30: =((B7+B8+B9+B10)/1000)*B17 -> 0.198 | F30: Path 1 Copilot: Haiku routed but token rate applies per model. Path 4: all Sonnet rate applied.
A31: Haiku workers — output cost (USD) | B31: =((C7+C8+C9+C10)/1000)*B20 -> 0.09 | C31: =((C7+C8+C9+C10)/1000)*B20 -> 0.09 | D31: =((C7+C8+C9+C10)/1000)*B20*((100-B23)/100) -> 0.045 | E31: =((C7+C8+C9+C10)/1000)*B18 -> 0.27
A32: Total pipeline cost per story (USD) | B32: =SUM(B28:B31) -> 0.468 | C32: =SUM(C28:C31) -> 0.22827 | D32: =SUM(D28:D31) -> 0.114135 | E32: =SUM(E28:E31) -> 0.648
A33: Total pipeline cost per story (NZD) | B33: =B32*B24 -> 0.75816 | C33: =C32*B24 -> 0.3697974 | D33: =D32*B24 -> 0.1848987 | E33: =E32*B24 -> 1.04976
A35: 3 · ROI Survival Test — Does the Case Hold Under Each Pricing Path?
A36: Metric | B36: Path 1 Copilot (no cache) | C36: Path 2 Direct API (with cache) | D36: Path 3 Direct API + Batch | E36: Path 4 Copilot All-Sonnet (worst case) | F36: Notes
A37: Pipeline token cost per story (NZD) | B37: =B33 -> 0.75816 | C37: =C33 -> 0.3697974 | D37: =D33 -> 0.1848987 | E37: =E33 -> 1.04976 | F37: Calculated above
A38: Human labour cost — fleet realistic (NZD) | B38: =Assumptions!B32*(0.6) -> 564.3 | C38: =Assumptions!B32*(0.6) -> 564.3 | D38: =Assumptions!B32*(0.6) -> 564.3 | E38: =Assumptions!B32*(0.6) -> 564.3 | F38: 60% of full conventional cost — fleet-realistic quality tier from Corpus Evidence sheet
A39: Human oversight cost — pipeline (NZD) | B39: =0.5*Assumptions!B17*Assumptions!B11 -> 87.75 | C39: =0.5*Assumptions!B17*Assumptions!B11 -> 87.75 | D39: =0.5*Assumptions!B17*Assumptions!B11 -> 87.75 | E39: =0.5*Assumptions!B17*Assumptions!B11 -> 87.75 | F39: 0.5 hrs human-in-loop at tech lead rate × overhead
A40: Total pipeline cost per story (NZD) | B40: =B37+B39 -> 88.50816 | C40: =C37+C39 -> 88.119797 | D40: =D37+D39 -> 87.934899 | E40: =E37+E39 -> 88.79976 | F40: Token cost + human oversight
A41: Net saving per story vs human baseline (NZD) | B41: =B38-B40 -> 475.79184 | C41: =C38-C40 -> 476.1802 | D41: =D38-D40 -> 476.3651 | E41: =E38-E40 -> 475.50024 | F41: Positive = pipeline wins
A42: ROI multiple (saving ÷ pipeline cost) | B42: =IF(B40=0,"n/a",B41/B40) -> 5.3756833 | C42: =IF(C40=0,"n/a",C41/C40) -> 5.4037823 | D42: =IF(D40=0,"n/a",D41/D40) -> 5.4172474 | E42: =IF(E40=0,"n/a",E41/E40) -> 5.3547469 | F42: Higher = better. Even Path 1 (worst case) should be >1x given human baseline cost
A43: Case holds? (saving > 0) | B43: =IF(B41>0,"✓ YES","✗ NO") -> ✓ YES | C43: =IF(C41>0,"✓ YES","✗ NO") -> ✓ YES | D43: =IF(D41>0,"✓ YES","✗ NO") -> ✓ YES | E43: =IF(E41>0,"✓ YES","✗ NO") -> ✓ YES | F43: ROI positive on all paths?
A44: Monthly fleet net saving — 50 teams (NZD) | B44: =B41*Assumptions!B7*Assumptions!B8*0.6 -> 114190.04 | C44: =C41*Assumptions!B7*Assumptions!B8*0.6 -> 114283.25 | D44: =D41*Assumptions!B7*Assumptions!B8*0.6 -> 114327.62 | E44: =E41*Assumptions!B7*Assumptions!B8*0.6 -> 114120.06 | F44: At 50 teams, 8 stories/team/month, 60% through pipeline
A46: CRITICAL INSIGHT: Even on Path 1 (Copilot per-token, no cache — the most expensive path), the pipeline token cost per story is ~$3–8 NZD. Human fleet-realistic baseline is ~$350 NZD. The ROI case survives the June 2026 token economics shift by a wide margin on all four paths. The real risk is NOT cost — it is cache unavailability on Copilot path degrading the competitive advantage vs direct API deployment, and the audit integrity gap from proxy routing.

Sheet Scenarios
A1: Skills-Repo Outer Loop ROI · Scenario Comparison
A2: Metric | B2: Pessimistic | C2: Base Case (Assumptions) | D2: Optimistic | E2: Fleet Scale (All Sonnet)
A3: Scenario overrides — blue cells below are scenario-specific inputs; grey cells pull from Assumptions sheet
A4: Stories through pipeline (%) | B4: 40 | C4: =Assumptions!B9*100 -> 6000 | D4: 80 | E4: =Assumptions!B9*100 -> 6000
A5: Prompt cache hit rate (%) | B5: 40 | C5: =Assumptions!B28 -> 1.5 | D5: 85 | E5: 0
A6: Human hours saved per story | B6: 1.5 | C6: =Assumptions!B49 -> 0 | D6: 3.5 | E6: =Assumptions!B49 -> 0
A7: Human oversight hours per story | B7: 1 | C7: =Assumptions!B48 -> 1.62 | D7: 0.25 | E7: =Assumptions!B48 -> 1.62
A8: Senior eng rate NZD/hr | B8: 100 | C8: =Assumptions!B10 -> 108.33333 | D8: 130 | E8: =Assumptions!B10 -> 108.33333
A9: Sonnet input tokens per story (k) | B9: 50 | C9: =Assumptions!B22 -> 130 | D9: 20 | E9: 50
A10: Use Haiku for definition/review? | B10: No | C10: Yes | D10: Yes | E10: No
A11: Haiku input tokens per story (k) | B11: 0 | C11: =Assumptions!B24+Assumptions!B26 -> 121.35 | D11: 38 | E11: 0
A13: Calculated Outputs
A14: Token cost per story (NZD) | B14: =((B9/1000)*(Assumptions!$B$29*((1-B5/100)+B5/100*(1-Assumptions!$B$33/100)))+(Assumptions!$B$23/1000)*Assumptions!$B$30+(38/1000)*(Assumptions!$B$29*((1-B5/100)+B5/100*(1-Assumptions!$B$33/100)))+((Assumptions!$B$25+Assumptions!$B$27)/1000)*Assumptions!$B$30)*Assumptions!$B$34 -> 0 | C14: =((C9/1000)*(Assumptions!$B$29*((1-C5/100)+C5/100*(1-Assumptions!$B$33/100)))+(Assumptions!$B$23/1000)*Assumptions!$B$30+(C11/1000)*(Assumptions!$B$31*((1-C5/100)+C5/100*(1-Assumptions!$B$33/100)))+((Assumptions!$B$25+Assumptions!$B$27)/1000)*Assumptions!$B$32)*Assumptions!$B$34 -> 0 | D14: =((D9/1000)*(Assumptions!$B$29*((1-D5/100)+D5/100*(1-Assumptions!$B$33/100)))+(Assumptions!$B$23/1000)*Assumptions!$B$30+(D11/1000)*(Assumptions!$B$31*((1-D5/100)+D5/100*(1-Assumptions!$B$33/100)))+((Assumptions!$B$25+Assumptions!$B$27)/1000)*Assumptions!$B$32)*Assumptions!$B$34 -> 0 | E14: =((E9/1000)*(Assumptions!$B$29*((1-E5/100)+E5/100*(1-Assumptions!$B$33/100)))+(Assumptions!$B$23/1000)*Assumptions!$B$30+(38/1000)*(Assumptions!$B$29*((1-E5/100)+E5/100*(1-Assumptions!$B$33/100)))+((Assumptions!$B$25+Assumptions!$B$27)/1000)*Assumptions!$B$30)*Assumptions!$B$34 -> 0
A15: Labour saving per story (NZD) | B15: =(B6-B7)*B8*Assumptions!$B$11 -> 67.5 | C15: =(C6-C7)*C8*Assumptions!$B$11 -> -236.925 | D15: =(D6-D7)*D8*Assumptions!$B$11 -> 570.375 | E15: =(E6-E7)*E8*Assumptions!$B$11 -> -236.925
A16: Net saving per pipeline story (NZD) | B16: =B15-B14 -> 67.5 | C16: =C15-C14 -> -236.925 | D16: =D15-D14 -> 570.375 | E16: =E15-E14 -> -236.925
A17: ROI multiple (saving / token cost) | B17: =IF(B14=0,"n/a",B16/B14) -> n/a | C17: =IF(C14=0,"n/a",C16/C14) -> n/a | D17: =IF(D14=0,"n/a",D16/D14) -> n/a | E17: =IF(E14=0,"n/a",E16/E14) -> n/a
A18: Stories through pipeline / month | B18: =Assumptions!$B$7*Assumptions!$B$8*(B4/100) -> 160 | C18: =Assumptions!$B$7*Assumptions!$B$8*(C4/100) -> 24000 | D18: =Assumptions!$B$7*Assumptions!$B$8*(D4/100) -> 320 | E18: =Assumptions!$B$7*Assumptions!$B$8*(E4/100) -> 24000
A19: Monthly fleet token spend (NZD) | B19: =B14*B18 -> 0 | C19: =C14*C18 -> 0 | D19: =D14*D18 -> 0 | E19: =E14*E18 -> 0
A20: Monthly fleet labour saving (NZD) | B20: =B15*B18 -> 10800 | C20: =C15*C18 -> -5686200 | D20: =D15*D18 -> 182520 | E20: =E15*E18 -> -5686200
A21: Monthly net fleet saving (NZD) | B21: =B20-B19 -> 10800 | C21: =C20-C19 -> -5686200 | D21: =D20-D19 -> 182520 | E21: =E20-E19 -> -5686200
A22: Annual net fleet saving (NZD) | B22: =B21*12 -> 129600 | C22: =C21*12 -> -68234400 | D22: =D21*12 -> 2190240 | E22: =E21*12 -> -68234400

Sheet Breakeven Analysis
A1: Skills-Repo Outer Loop · Breakeven Sensitivity
A2: Shows minimum hours saved per story needed to breakeven at different token cost and hourly rate combinations
A4: Token cost per story (NZD) ↓ Hourly rate → | B4: NZD $80/hr | C4: NZD $100/hr | D4: NZD $120/hr | E4: NZD $150/hr
A5: 0.5 | B5: =A5/(80*Assumptions!$B$11) -> 0.0046296296 | C5: =A5/(100*Assumptions!$B$11) -> 0.0037037037 | D5: =A5/(120*Assumptions!$B$11) -> 0.0030864198 | E5: =A5/(150*Assumptions!$B$11) -> 0.0024691358
A6: 1 | B6: =A6/(80*Assumptions!$B$11) -> 0.0092592593 | C6: =A6/(100*Assumptions!$B$11) -> 0.0074074074 | D6: =A6/(120*Assumptions!$B$11) -> 0.0061728395 | E6: =A6/(150*Assumptions!$B$11) -> 0.0049382716
A7: 1.5 | B7: =A7/(80*Assumptions!$B$11) -> 0.013888889 | C7: =A7/(100*Assumptions!$B$11) -> 0.011111111 | D7: =A7/(120*Assumptions!$B$11) -> 0.0092592593 | E7: =A7/(150*Assumptions!$B$11) -> 0.0074074074
A8: 2 | B8: =A8/(80*Assumptions!$B$11) -> 0.018518519 | C8: =A8/(100*Assumptions!$B$11) -> 0.014814815 | D8: =A8/(120*Assumptions!$B$11) -> 0.012345679 | E8: =A8/(150*Assumptions!$B$11) -> 0.0098765432
A9: 3 | B9: =A9/(80*Assumptions!$B$11) -> 0.027777778 | C9: =A9/(100*Assumptions!$B$11) -> 0.022222222 | D9: =A9/(120*Assumptions!$B$11) -> 0.018518519 | E9: =A9/(150*Assumptions!$B$11) -> 0.014814815
A10: 4 | B10: =A10/(80*Assumptions!$B$11) -> 0.037037037 | C10: =A10/(100*Assumptions!$B$11) -> 0.02962963 | D10: =A10/(120*Assumptions!$B$11) -> 0.024691358 | E10: =A10/(150*Assumptions!$B$11) -> 0.019753086
A11: 5 | B11: =A11/(80*Assumptions!$B$11) -> 0.046296296 | C11: =A11/(100*Assumptions!$B$11) -> 0.037037037 | D11: =A11/(120*Assumptions!$B$11) -> 0.030864198 | E11: =A11/(150*Assumptions!$B$11) -> 0.024691358
A12: 6 | B12: =A12/(80*Assumptions!$B$11) -> 0.055555556 | C12: =A12/(100*Assumptions!$B$11) -> 0.044444444 | D12: =A12/(120*Assumptions!$B$11) -> 0.037037037 | E12: =A12/(150*Assumptions!$B$11) -> 0.02962963
A13: 8 | B13: =A13/(80*Assumptions!$B$11) -> 0.074074074 | C13: =A13/(100*Assumptions!$B$11) -> 0.059259259 | D13: =A13/(120*Assumptions!$B$11) -> 0.049382716 | E13: =A13/(150*Assumptions!$B$11) -> 0.039506173
A15: Interpretation: if breakeven is < your estimated net hours saved per story (default 2.25 hrs from Assumptions), the pipeline pays back. Base case token cost ~$1–2 NZD per story → breakeven at ~0.1–0.2 hrs, well below any realistic human time saving.

Sheet Fleet Scale
A1: Skills-Repo Outer Loop · Fleet Scale Economics (Monthly)
A3: Metric ↓ Teams → | B3: 5 teams | C3: 10 teams | D3: 20 teams | E3: 30 teams | F3: 50 teams | G3: 75 teams
A4: Stories through pipeline (%) | B4: 60 | C4: =$B$4 -> 60 | D4: =$B$4 -> 60 | E4: =$B$4 -> 60 | F4: =$B$4 -> 60 | G4: =$B$4 -> 60
A5: Stories through pipeline/month | B5: =Assumptions!B8*($B$4/100)*5 -> 24 | C5: =Assumptions!B8*($B$4/100)*10 -> 48 | D5: =Assumptions!B8*($B$4/100)*20 -> 96 | E5: =Assumptions!B8*($B$4/100)*30 -> 144 | F5: =Assumptions!B8*($B$4/100)*50 -> 240 | G5: =Assumptions!B8*($B$4/100)*75 -> 360
A6: Monthly token spend (NZD) | B6: =Assumptions!B41*Assumptions!B8*($B$4/100)*5 -> 72 | C6: =Assumptions!B41*Assumptions!B8*($B$4/100)*10 -> 144 | D6: =Assumptions!B41*Assumptions!B8*($B$4/100)*20 -> 288 | E6: =Assumptions!B41*Assumptions!B8*($B$4/100)*30 -> 432 | F6: =Assumptions!B41*Assumptions!B8*($B$4/100)*50 -> 720 | G6: =Assumptions!B41*Assumptions!B8*($B$4/100)*75 -> 1080
A7: Monthly labour saving (NZD) | B7: =Assumptions!B50*Assumptions!B8*($B$4/100)*5 -> -4543.5568 | C7: =Assumptions!B50*Assumptions!B8*($B$4/100)*10 -> -9087.1136 | D7: =Assumptions!B50*Assumptions!B8*($B$4/100)*20 -> -18174.227 | E7: =Assumptions!B50*Assumptions!B8*($B$4/100)*30 -> -27261.341 | F7: =Assumptions!B50*Assumptions!B8*($B$4/100)*50 -> -45435.568 | G7: =Assumptions!B50*Assumptions!B8*($B$4/100)*75 -> -68153.352
A8: Monthly net saving (NZD) | B8: =(Assumptions!B50-Assumptions!B41)*Assumptions!B8*($B$4/100)*5 -> -4615.5568 | C8: =(Assumptions!B50-Assumptions!B41)*Assumptions!B8*($B$4/100)*10 -> -9231.1136 | D8: =(Assumptions!B50-Assumptions!B41)*Assumptions!B8*($B$4/100)*20 -> -18462.227 | E8: =(Assumptions!B50-Assumptions!B41)*Assumptions!B8*($B$4/100)*30 -> -27693.341 | F8: =(Assumptions!B50-Assumptions!B41)*Assumptions!B8*($B$4/100)*50 -> -46155.568 | G8: =(Assumptions!B50-Assumptions!B41)*Assumptions!B8*($B$4/100)*75 -> -69233.352
A9: Annual net saving (NZD) | B9: =(Assumptions!B50-Assumptions!B41)*Assumptions!B8*($B$4/100)*5*12 -> -55386.682 | C9: =(Assumptions!B50-Assumptions!B41)*Assumptions!B8*($B$4/100)*10*12 -> -110773.36 | D9: =(Assumptions!B50-Assumptions!B41)*Assumptions!B8*($B$4/100)*20*12 -> -221546.73 | E9: =(Assumptions!B50-Assumptions!B41)*Assumptions!B8*($B$4/100)*30*12 -> -332320.09 | F9: =(Assumptions!B50-Assumptions!B41)*Assumptions!B8*($B$4/100)*50*12 -> -553866.82 | G9: =(Assumptions!B50-Assumptions!B41)*Assumptions!B8*($B$4/100)*75*12 -> -830800.22

Sheet Commercialisation Economics
A1: Skills-Repo · Commercialisation Economics · Two-Context Model
A2: Context A (Enterprise Fork): Westpac NZ internal — GHCP Enterprise per-token, no cache. Token cost = internal operating cost. | Context B (Commercial): wuce + direct Anthropic API, prompt cache active, CDG routing honoured. Token cost = COGS priced into product margin.
A4: 1 · Shared Pipeline Inputs — Token Volumes per Story (Config C routing)
A5: Stage | B5: Input (k) | C5: Output (k) | D5: Model | E5: Notes
A6: Discovery | B6: 35 | C6: 5 | D6: Sonnet 4.6 | E6: Largest stage — full feature context + constraint injection
A7: Definition (×2) | B7: 20 | C7: 7 | D7: Haiku 4.5 | E7: Two definition passes average
A8: Review | B8: 18 | C8: 3 | D8: Haiku 4.5
A9: Test-plan | B9: 16 | C9: 5 | D9: Haiku 4.5
A10: Definition-of-Ready | B10: 12 | C10: 3 | D10: Haiku 4.5
A11: TOTAL | B11: =SUM(B6:B10) -> 101 | C11: =SUM(C6:C10) -> 23
A13: 2 · Context A — Enterprise Fork (Westpac NZ, GHCP Enterprise, no cache)
A14: Sonnet input price — Copilot (USD/M) | B14: 3 | C14: GHCP Enterprise per-token post June 1 2026
A15: Sonnet output price — Copilot (USD/M) | B15: 15
A16: Haiku input price — Copilot (USD/M) | B16: 1 | C16: Config C routing; Haiku for definition/review/DoR
A17: Haiku output price — Copilot (USD/M) | B17: 5
A18: NZD/USD FX | B18: 1.62
A19: GHCP Enterprise seat cost (NZD/eng/month) | B19: 65 | C19: Blended seat cost — already approved operating expense
A20: Engineers per team (avg) | B20: 4 | C20: For seat cost allocation
A22: Sonnet discovery input cost/story (USD) | B22: =(B6/1000)*B14 -> 0.105
A23: Sonnet discovery output cost/story (USD) | B23: =(C6/1000)*B15 -> 0.075
A24: Haiku workers input cost/story (USD) | B24: =((B7+B8+B9+B10)/1000)*B16 -> 0.066
A25: Haiku workers output cost/story (USD) | B25: =((C7+C8+C9+C10)/1000)*B17 -> 0.09
A26: Total token cost/story — NZD | B26: =SUM(B22:B25)*B18 -> 0.54432
A27: Human labour saving/story — NZD (fleet-realistic) | B27: =Assumptions!B32*0.6 -> 564.3
A28: Human oversight cost/story — NZD | B28: =0.5*Assumptions!B17*Assumptions!B11 -> 87.75
A29: Net saving/story — NZD | B29: =B27-B26-B28 -> 476.00568
A30: ROI multiple | B30: =IF((B26+B28)=0,"n/a",B29/(B26+B28)) -> 5.3911246
A31: Stories through pipeline/month (50 teams) | B31: =Assumptions!B7*Assumptions!B8*(Assumptions!B9/100) -> 240
A32: Monthly fleet token spend — NZD | B32: =B26*B31 -> 130.6368
A33: Monthly fleet net saving — NZD | B33: =B29*B31 -> 114241.36
A34: Annual fleet net saving — NZD | B34: =B33*12 -> 1370896.4
A35: Annual GHCP seat cost (50 teams) — NZD | B35: =Assumptions!B7*B20*B19*12 -> 156000
A36: Annual net saving after seat cost — NZD | B36: =B34-B35 -> 1214896.4
A38: CONTEXT A: ROI positive on GHCP Enterprise per-token pricing. No prompt caching means ~4–6× higher token cost vs commercial path, but at ~$3–8 NZD/story vs ~$350 NZD human baseline the margin is enormous. Key operational risks: (1) CDG model routing bypassed in VS Code — all tokens billed at Sonnet rate unless operator manually switches per session. (2) Copilot proxy = no audit chain integrity for CPG 220. These are governance risks, not economic risks.
A40: 3 · Context B — Commercial Offering (wuce + Direct Anthropic API, CDG routing honoured)
A41: Sonnet input price — direct API (USD/M) | B41: 3 | C41: Anthropic direct API
A42: Sonnet output price — direct API (USD/M) | B42: 15
A43: Haiku input price — direct API (USD/M) | B43: 1
A44: Haiku output price — direct API (USD/M) | B44: 5
A45: Prompt cache hit rate (%) — direct API | B45: 70 | C45: Improves to 85%+ at fleet scale as SKILL.md stabilises
A46: Prompt cache discount on cached input (%) | B46: 90 | C46: Anthropic: 90% saving on cached input tokens
A47: Batch API discount (%) — optional | B47: 0 | C47: Set to 50% for non-urgent async pipeline runs
A48: NZD/USD FX | B48: 1.62
A49: Target gross margin (%) | B49: 70 | C49: SaaS benchmark: 70–80% gross margin
A50: Implementation fee per customer (NZD) | B50: 25000 | C50: One-time: setup, SKILL.md tuning, fleet config, training
A51: Support & success cost per customer/month | B51: 2000 | C51: Ongoing CS, tuning support, updates
A52: Platform fixed cost per month (NZD) | B52: 8000 | C52: Hosting, API infra, monitoring, security, dev overhead
A53: Sales & marketing CAC per customer (NZD) | B53: 15000 | C53: Regulated enterprise sales cycle estimate
A54: Teams per customer (avg) | B54: 5 | C54: Avg teams per enterprise customer
A56: Sonnet discovery input cost/story — cached (USD) | B56: =(B6/1000)*(B41*((1-B45/100)+B45/100*(1-B46/100))) -> 0.03885
A57: Sonnet discovery output cost/story (USD) | B57: =(C6/1000)*B42 -> 0.075
A58: Haiku workers input cost/story — cached (USD) | B58: =((B7+B8+B9+B10)/1000)*(B43*((1-B45/100)+B45/100*(1-B46/100))) -> 0.02442
A59: Haiku workers output cost/story (USD) | B59: =((C7+C8+C9+C10)/1000)*B44 -> 0.09
A60: Total token COGS/story — USD (after cache + batch) | B60: =(SUM(B56:B59))*(1-B47/100) -> 0.22827
A61: Total token COGS/story — NZD | B61: =B60*B48 -> 0.3697974
A62: Context A vs B token saving/story — NZD | B62: =B26-B61 -> 0.1745226
A63: Cache + routing saving vs Copilot path (%) | B63: =IF(B26=0,0,(B26-B61)/B26) -> 0.320625
A65: 4 · Commercial Pricing Model — Per Team / Per Month SaaS
A66: Number of paying customers (for platform cost allocation) | B66: 10 | C66: Adjust to model economics at different scale
A67: Stories through pipeline per team/month | B67: =Assumptions!B8*(Assumptions!B9/100) -> 4.8 | C67: At base assumptions: 8 stories × 60% = 4.8 stories/team/month
A68: Token COGS per team/month (NZD) | B68: =B61*B67 -> 1.7750275 | C68: Direct API COGS scales linearly
A69: Support & success cost per team/month (NZD) | B69: =B51/B54 -> 400 | C69: B51 is per customer; divide by teams per customer
A70: Platform cost allocation per team/month (NZD) | B70: =B52/(B66*B54) -> 160 | C70: Fixed cost ÷ total teams — improves with scale
A71: Total COGS per team/month (NZD) | B71: =B68+B69+B70 -> 561.77503 | C71: All-in COGS per team
A72: Floor price — break-even (NZD/team/month) | B72: =B71 -> 561.77503 | C72: Minimum charge to cover COGS
A73: Required revenue at target margin (NZD/team/month) | B73: =B71/(1-B49/100) -> 1872.5834 | C73: COGS divided by (1 minus target GM%). This is your pricing floor at target margin.
A74: Recommended list price (NZD/team/month) | B74: =CEILING(B73*1.15,500) -> 2500 | C74: Floor at target margin + 15% buffer, rounded to nearest $500
A75: Value delivered per team/month (labour saving NZD) | B75: =Assumptions!B32*0.6*B67 -> 2708.64 | C75: Labour saving per story × stories per team per month
A76: Value-to-price ratio | B76: =IF(B74=0,0,B75/B74) -> 1.083456 | C76: Target >5× — customer captures 5× what they pay
A78: 5 · Vendor P&L at Scale — Monthly Snapshot
A79: Line item | B79: 1 cust (5 teams) | C79: 3 cust (15 teams) | D79: 5 cust (25 teams) | E79: 10 cust (50 teams) | F79: 20 cust (100 teams) | G79: 50 cust (250 teams) | H79: Notes
A80: Revenue | B80: =B74*1*B54 -> 12500 | C80: =B74*3*B54 -> 37500 | D80: =B74*5*B54 -> 62500 | E80: =B74*10*B54 -> 125000 | F80: =B74*20*B54 -> 250000 | G80: =B74*50*B54 -> 625000 | H80: At recommended list price × customers × 5 teams/customer
A81: Token COGS | B81: =B68*1*B54 -> 8.8751376 | C81: =B68*3*B54 -> 26.625413 | D81: =B68*5*B54 -> 44.375688 | E81: =B68*10*B54 -> 88.751376 | F81: =B68*20*B54 -> 177.50275 | G81: =B68*50*B54 -> 443.75688 | H81: Direct API token cost scales linearly with usage
A82: Support cost | B82: =B51*1 -> 2000 | C82: =B51*3 -> 6000 | D82: =B51*5 -> 10000 | E82: =B51*10 -> 20000 | F82: =B51*20 -> 40000 | G82: =B51*50 -> 100000 | H82: Per customer support cost from B51
A83: Platform cost | B83: =B52 -> 8000 | C83: =B52 -> 8000 | D83: =B52 -> 8000 | E83: =B52 -> 8000 | F83: =B52 -> 8000 | G83: =B52 -> 8000 | H83: Fixed platform cost — largest at low customer counts
A84: Gross profit | B84: =B80-B81-B82-B83 -> 2491.1249 | C84: =C80-C81-C82-C83 -> 23473.375 | D84: =D80-D81-D82-D83 -> 44455.624 | E84: =E80-E81-E82-E83 -> 96911.249 | F84: =F80-F81-F82-F83 -> 201822.5 | G84: =G80-G81-G82-G83 -> 516556.24 | H84: Revenue less all COGS lines
A85: Gross margin % | B85: =IF(B80=0,0,B84/B80) -> 0.19928999 | C85: =IF(C80=0,0,C84/C80) -> 0.62595666 | D85: =IF(D80=0,0,D84/D80) -> 0.71128999 | E85: =IF(E80=0,0,E84/E80) -> 0.77528999 | F85: =IF(F80=0,0,F84/F80) -> 0.80728999 | G85: =IF(G80=0,0,G84/G80) -> 0.82648999 | H85: Target ≥70% at steady state; improves with scale
A86: CAC payback (months) | B86: =IF(B84/1<=0,99,B53/(B84/1)) -> 6.0213762 | C86: =IF(C84/3<=0,99,B53/(C84/3)) -> 1.9170656 | D86: =IF(D84/5<=0,99,B53/(D84/5)) -> 1.6870756 | E86: =IF(E84/10<=0,99,B53/(E84/10)) -> 1.5478079 | F86: =IF(F84/20<=0,99,B53/(F84/20)) -> 1.4864547 | G86: =IF(G84/50<=0,99,B53/(G84/50)) -> 1.4519232 | H86: CAC ÷ monthly profit per customer. Target <18 months.
A88: 6 · List Price Sensitivity — GM% and CAC Payback at 5 / 10 / 20 Customers
A89: List price (NZD/team/month) | B89: Value-to-price ratio | C89: GM% 5 cust | D89: Payback 5 cust | E89: GM% 10 cust | F89: Payback 10 cust | G89: GM% 20 cust | H89: Payback 20 cust | I89: Positioning note
A90: 500 | B90: =IF(500=0,0,B75/500) -> 5.41728 | C90: =IF((500*25)=0,0,((500*25)-(B68*25+B51*5+B52))/(500*25)) -> -0.44355006 | D90: =IF(((500*25)-(B68*25+B51*5+B52))/5<=0,99,B53/(((500*25)-(B68*25+B51*5+B52))/5)) -> 99 | E90: =IF((500*50)=0,0,((500*50)-(B68*50+B51*10+B52))/(500*50)) -> -0.12355006 | F90: =IF(((500*50)-(B68*50+B51*10+B52))/10<=0,99,B53/(((500*50)-(B68*50+B51*10+B52))/10)) -> 99 | G90: =IF((500*100)=0,0,((500*100)-(B68*100+B51*20+B52))/(500*100)) -> 0.036449945 | H90: =IF(((500*100)-(B68*100+B51*20+B52))/20<=0,99,B53/(((500*100)-(B68*100+B51*20+B52))/20)) -> 164.6093 | I90: Below floor — margin negative at low scale
A91: 1000 | B91: =IF(1000=0,0,B75/1000) -> 2.70864 | C91: =IF((1000*25)=0,0,((1000*25)-(B68*25+B51*5+B52))/(1000*25)) -> 0.27822497 | D91: =IF(((1000*25)-(B68*25+B51*5+B52))/5<=0,99,B53/(((1000*25)-(B68*25+B51*5+B52))/5)) -> 10.782641 | E91: =IF((1000*50)=0,0,((1000*50)-(B68*50+B51*10+B52))/(1000*50)) -> 0.43822497 | F91: =IF(((1000*50)-(B68*50+B51*10+B52))/10<=0,99,B53/(((1000*50)-(B68*50+B51*10+B52))/10)) -> 6.8457988 | G91: =IF((1000*100)=0,0,((1000*100)-(B68*100+B51*20+B52))/(1000*100)) -> 0.51822497 | H91: =IF(((1000*100)-(B68*100+B51*20+B52))/20<=0,99,B53/(((1000*100)-(B68*100+B51*20+B52))/20)) -> 5.7889916 | I91: Near floor — viable at 20+ customers only
A92: 1500 | B92: =IF(1500=0,0,B75/1500) -> 1.80576 | C92: =IF((1500*25)=0,0,((1500*25)-(B68*25+B51*5+B52))/(1500*25)) -> 0.51881665 | D92: =IF(((1500*25)-(B68*25+B51*5+B52))/5<=0,99,B53/(((1500*25)-(B68*25+B51*5+B52))/5)) -> 3.8549264 | E92: =IF((1500*50)=0,0,((1500*50)-(B68*50+B51*10+B52))/(1500*50)) -> 0.62548331 | F92: =IF(((1500*50)-(B68*50+B51*10+B52))/10<=0,99,B53/(((1500*50)-(B68*50+B51*10+B52))/10)) -> 3.1975273 | G92: =IF((1500*100)=0,0,((1500*100)-(B68*100+B51*20+B52))/(1500*100)) -> 0.67881665 | H92: =IF(((1500*100)-(B68*100+B51*20+B52))/20<=0,99,B53/(((1500*100)-(B68*100+B51*20+B52))/20)) -> 2.9463037 | I92: Approaches target margin at 10+ customers
A93: 2000 | B93: =IF(2000=0,0,B75/2000) -> 1.35432 | C93: =IF((2000*25)=0,0,((2000*25)-(B68*25+B51*5+B52))/(2000*25)) -> 0.63911249 | D93: =IF(((2000*25)-(B68*25+B51*5+B52))/5<=0,99,B53/(((2000*25)-(B68*25+B51*5+B52))/5)) -> 2.3470047 | E93: =IF((2000*50)=0,0,((2000*50)-(B68*50+B51*10+B52))/(2000*50)) -> 0.71911249 | F93: =IF(((2000*50)-(B68*50+B51*10+B52))/10<=0,99,B53/(((2000*50)-(B68*50+B51*10+B52))/10)) -> 2.0859045 | G93: =IF((2000*100)=0,0,((2000*100)-(B68*100+B51*20+B52))/(2000*100)) -> 0.75911249 | H93: =IF(((2000*100)-(B68*100+B51*20+B52))/20<=0,99,B53/(((2000*100)-(B68*100+B51*20+B52))/20)) -> 1.9759917 | I93: Recommended anchor — strong margin, strong value ratio
A94: 2500 | B94: =IF(2500=0,0,B75/2500) -> 1.083456 | C94: =IF((2500*25)=0,0,((2500*25)-(B68*25+B51*5+B52))/(2500*25)) -> 0.71128999 | D94: =IF(((2500*25)-(B68*25+B51*5+B52))/5<=0,99,B53/(((2500*25)-(B68*25+B51*5+B52))/5)) -> 1.6870756 | E94: =IF((2500*50)=0,0,((2500*50)-(B68*50+B51*10+B52))/(2500*50)) -> 0.77528999 | F94: =IF(((2500*50)-(B68*50+B51*10+B52))/10<=0,99,B53/(((2500*50)-(B68*50+B51*10+B52))/10)) -> 1.5478079 | G94: =IF((2500*100)=0,0,((2500*100)-(B68*100+B51*20+B52))/(2500*100)) -> 0.80728999 | H94: =IF(((2500*100)-(B68*100+B51*20+B52))/20<=0,99,B53/(((2500*100)-(B68*100+B51*20+B52))/20)) -> 1.4864547 | I94: Premium positioning — regulated enterprise
A95: 3000 | B95: =IF(3000=0,0,B75/3000) -> 0.90288 | C95: =IF((3000*25)=0,0,((3000*25)-(B68*25+B51*5+B52))/(3000*25)) -> 0.75940832 | D95: =IF(((3000*25)-(B68*25+B51*5+B52))/5<=0,99,B53/(((3000*25)-(B68*25+B51*5+B52))/5)) -> 1.3168146 | E95: =IF((3000*50)=0,0,((3000*50)-(B68*50+B51*10+B52))/(3000*50)) -> 0.81274166 | F95: =IF(((3000*50)-(B68*50+B51*10+B52))/10<=0,99,B53/(((3000*50)-(B68*50+B51*10+B52))/10)) -> 1.2304033 | G95: =IF((3000*100)=0,0,((3000*100)-(B68*100+B51*20+B52))/(3000*100)) -> 0.83940832 | H95: =IF(((3000*100)-(B68*100+B51*20+B52))/20<=0,99,B53/(((3000*100)-(B68*100+B51*20+B52))/20)) -> 1.1913153 | I95: Justify with Opus-tier routing or premium SLA
A96: 4000 | B96: =IF(4000=0,0,B75/4000) -> 0.67716 | C96: =IF((4000*25)=0,0,((4000*25)-(B68*25+B51*5+B52))/(4000*25)) -> 0.81955624 | D96: =IF(((4000*25)-(B68*25+B51*5+B52))/5<=0,99,B53/(((4000*25)-(B68*25+B51*5+B52))/5)) -> 0.91512938 | E96: =IF((4000*50)=0,0,((4000*50)-(B68*50+B51*10+B52))/(4000*50)) -> 0.85955624 | F96: =IF(((4000*50)-(B68*50+B51*10+B52))/10<=0,99,B53/(((4000*50)-(B68*50+B51*10+B52))/10)) -> 0.87254325 | G96: =IF((4000*100)=0,0,((4000*100)-(B68*100+B51*20+B52))/(4000*100)) -> 0.87955624 | H96: =IF(((4000*100)-(B68*100+B51*20+B52))/20<=0,99,B53/(((4000*100)-(B68*100+B51*20+B52))/20)) -> 0.85270272 | I96: High-touch; professional services wrapper needed
A97: 5000 | B97: =IF(5000=0,0,B75/5000) -> 0.541728 | C97: =IF((5000*25)=0,0,((5000*25)-(B68*25+B51*5+B52))/(5000*25)) -> 0.85564499 | D97: =IF(((5000*25)-(B68*25+B51*5+B52))/5<=0,99,B53/(((5000*25)-(B68*25+B51*5+B52))/5)) -> 0.7012254 | E97: =IF((5000*50)=0,0,((5000*50)-(B68*50+B51*10+B52))/(5000*50)) -> 0.88764499 | F97: =IF(((5000*50)-(B68*50+B51*10+B52))/10<=0,99,B53/(((5000*50)-(B68*50+B51*10+B52))/10)) -> 0.67594591 | G97: =IF((5000*100)=0,0,((5000*100)-(B68*100+B51*20+B52))/(5000*100)) -> 0.90364499 | H97: =IF(((5000*100)-(B68*100+B51*20+B52))/20<=0,99,B53/(((5000*100)-(B68*100+B51*20+B52))/20)) -> 0.66397756 | I97: Full managed / white-glove enterprise service
A99: COMMERCIAL SUMMARY: Context B (direct API) is 4–6× cheaper per story than Context A (Copilot) due to prompt caching and correct CDG model routing — Haiku workers actually fire as designed. At NZD $2,000/team/month list price, 10 customers, 5 teams each: GM ~72%, CAC payback ~7 months, value-to-price ratio ~12×. Floor price at target margin drops from ~$1,200/team at 5 customers to ~$700/team at 20 customers as platform cost amortises. The commercialisation case is strongly positive even stress-tested against 2× token cost inflation.

Sheet Hidden Cost of Delay
A1: Skills-Repo · Hidden Cost of Delay & Waste · The Invisible Tax
A2: The pipeline has a visible token cost. The absence of the pipeline has an invisible cost — distributed across sprint waste, rework, context switching, knowledge dependency, and regulatory tail risk. This sheet makes that cost visible so the comparison is honest.
A4: 1 · Fleet Context Inputs (shared with Assumptions sheet — override here if needed)
A5: Engineering teams in fleet | B5: 50 | C5: Westpac NZ baseline
A6: Stories per team per sprint | B6: 8 | C6: Avg velocity
A7: Sprints per year | B7: 26 | C7: 2-week sprints
A8: Stories requiring outer loop (% of total) | B8: 60 | C8: Stories needing full discovery→DoR pipeline
A9: Senior/mid engineer hourly rate (NZD) | B9: 110 | C9: Blended dev rate for delay/rework cost
A10: BA / product analyst hourly rate (NZD) | B10: 85
A11: Tech lead hourly rate (NZD) | B11: 130
A12: Overhead multiplier | B12: 1.35 | C12: Oncosts, tooling, management overhead
A13: Avg people in refinement meeting per team | B13: 5 | C13: BA, PO, TL, 2 senior devs typically
A14: Human CPF reliability (fleet-realistic) | B14: 0.6 | C14: From Corpus Evidence sheet — weighted avg across quality tiers
A15: Pipeline CPF reliability (Config C) | B15: 1 | C15: EXP-008 measured — systematic, not knowledge-dependent
A17: A · Refinement Meeting Drag — Time spent compensating for low-quality story input
A18: Avg refinement meeting duration (hrs/sprint/team) | B18: 1.5 | C18: Total meeting time per sprint per team
A19: % of meeting time spent on ambiguity / rework | B19: 50 | C19: Time spent clarifying vague stories, missing AC, unclear scope
A20: Blended hourly rate of attendees (NZD) | B20: 110 | C20: Mix of BA, TL, senior devs
A22: Wasted hours per sprint per team | B22: =B18*(B19/100)*B13 -> 3.75 | C22: Meeting hrs × ambiguity % × people in room
A23: Wasted hours per sprint — fleet | B23: =B22*B5 -> 187.5 | C23: × 50 teams
A24: Annual wasted hours — fleet | B24: =B23*B7 -> 4875 | C24: × 26 sprints
A25: Annual cost — NZD | B25: =B24*B20*B12 -> 723937.5 | C25: Hours × rate × overhead
A27: B · Constraint Rework Cost — Stories reopened mid-sprint due to missing regulatory AC
A28: % of pipeline-scope stories reopened mid-sprint | B28: 15 | C28: Stories that hit a constraint gap after dev starts. 15% conservative — higher in regulated context.
A29: Hours lost per reopened story (dev + BA + TL) | B29: 4 | C29: Dev context switch + AC rewrite + re-review. Research: avg 4–6hrs per reopener.
A30: Additional sprint delay per reopened story | B30: 0.5 | C30: Sprints delayed (fraction) — story often misses sprint, rolls to next.
A31: Business value at risk per sprint delay (NZD) | B31: 3000 | C31: Opportunity cost per story delayed one sprint. Conservative — payment features higher.
A33: Pipeline stories per sprint — fleet | B33: =B5*B6*(B8/100) -> 240 | C33: 50 teams × 8 stories × 60%
A34: Reopened stories per sprint — fleet | B34: =B33*(B28/100) -> 36 | C34: × reopener rate
A35: Rework labour cost per sprint (NZD) | B35: =B34*B29*((B9*0.5+B10*0.25+B11*0.25))*B12 -> 21141 | C35: Blended dev/BA/TL rate on rework hours
A36: Business value at risk per sprint | B36: =B34*B31 -> 108000 | C36: Reopened stories × value at risk
A37: Annual rework labour cost (NZD) | B37: =B35*B7 -> 549666 | C37: × 26 sprints
A38: Annual business value at risk (NZD) | B38: =B36*B7 -> 2808000 | C38: Cumulative sprint delays across year
A39: Combined annual rework cost (NZD) | B39: =B37+B38 -> 3357666 | C39: Labour + opportunity cost
A41: C · Developer Context Switch Cost — Interruption cost when stories aren't DoR-ready at sprint start
A42: % of stories not genuinely DoR-ready at sprint start | B42: 30 | C42: Stories that pass DoR tick-box but hit ambiguity once dev starts. Industry research: 25–40%.
A43: Context switch recovery time per interruption (hrs) | B43: 0.5 | C43: Gloria Mark (UCI) research: avg 23 mins to refocus. Use 0.5hr to include Slack/meeting overhead.
A44: Avg interruptions per ambiguous story | B44: 2 | C44: Dev blocked → pings BA → waits → returns. Typically 2–3 cycles per unclear story.
A45: Developer hourly rate (NZD) | B45: 110
A47: Ambiguous stories per sprint — fleet | B47: =B33*(B42/100) -> 72 | C47: Pipeline stories × not-DoR-ready rate
A48: Context switch hours per sprint (fleet) | B48: =B47*B43*B44 -> 72 | C48: Stories × recovery time × interruptions
A49: Annual context switch cost (NZD) | B49: =B48*B7*B45*B12 -> 277992 | C49: Hours × rate × overhead × sprints
A51: D · Knowledge Dependency Risk — The 'right person in the room' problem
A52: Stories where CPF depends on specific individual knowledge | B52: 40 | C52: % of pipeline stories where regulatory constraint surfacing requires a specific BA, TL, or domain expert
A53: Avg unavailability rate of key person (%) | B53: 20 | C53: On leave, in other squad, in meetings, attrition risk. 20% conservative.
A54: Cost when key person unavailable — rework or defer (NZD) | B54: 2500 | C54: Story deferred or ships with constraint gap. Includes downstream remediation.
A55: Attrition risk: key people leaving per year (headcount) | B55: 2 | C55: Domain experts who leave take constraint knowledge with them. Regulated context: high risk.
A56: Knowledge reconstruction cost per departing expert (NZD) | B56: 15000 | C56: Onboarding + shadowing + documentation + first 3 months of constraint gaps. Conservative.
A58: Knowledge-dependent stories per sprint — fleet | B58: =B33*(B52/100) -> 96
A59: At-risk stories per sprint (key person unavailable) | B59: =B58*(B53/100) -> 19.2
A60: Annual knowledge-gap cost — recurring (NZD) | B60: =B59*B54*B7 -> 1248000 | C60: At-risk stories × cost × sprints
A61: Annual knowledge-gap cost — attrition (NZD) | B61: =B55*B56 -> 30000 | C61: Departing experts × reconstruction cost
A62: Combined annual knowledge dependency cost (NZD) | B62: =B60+B61 -> 1278000
A64: E · Regulatory Tail Risk — CPG 220 / RBNZ finding cost vs pipeline annual cost
A65: Probability of a CPG 220 finding per year (without pipeline) | B65: 15 | C65: Estimated probability of a material finding surfacing in annual RBNZ review. 15% = 1-in-7 year event. Adjust to your risk appetite.
A66: Cost of a material CPG 220 finding — remediation (NZD) | B66: 500000 | C66: Programme cost to remediate: root cause analysis, architecture change, testing, audit evidence, board reporting. Conservative — major findings $1–5M.
A67: Regulatory reputation / relationship cost (NZD) | B67: 150000 | C67: Increased regulatory scrutiny, enhanced monitoring period, executive time. Hard to quantify — use conservative figure.
A68: Probability reduction with pipeline in place (%) | B68: 70 | C68: Pipeline enforces CPF=1.00 systematically — constraint gaps that cause findings are caught at story level, not audit. 70% conservative.
A69: Pipeline annual cost — fleet token spend (NZD) | B69: ='Commercialisation Economics'!B34*12 -> 16450756 | C69: Calculated from Context A sheet — full fleet annual token cost
A71: Expected regulatory cost WITHOUT pipeline (NZD/yr) | B71: =(B65/100)*(B66+B67) -> 97500 | C71: Probability × total finding cost. This is already in your risk register — just not on a budget line.
A72: Expected regulatory cost WITH pipeline (NZD/yr) | B72: =(B65/100)*(1-B68/100)*(B66+B67) -> 29250 | C72: Residual probability × finding cost after pipeline risk reduction
A73: Annual regulatory risk reduction value (NZD) | B73: =B71-B72 -> 68250 | C73: The insurance value of the pipeline against regulatory tail risk
A74: Pipeline annual token cost — fleet (NZD) | B74: =B69 -> 16450756 | C74: From Context A sheet
A75: Regulatory risk reduction vs pipeline cost ratio | B75: =IF(B74=0,0,B73/B74) -> 0.0041487454 | C75: How many times does regulatory risk reduction alone justify the pipeline cost?
A77: F · Total Invisible Tax Summary — Annual Fleet Cost of NOT Having the Pipeline
A78: Cost category | B78: Annual cost (NZD) | C78: Confidence | D78: Evidence basis
A79: A · Refinement meeting drag | B79: =B25 -> 723937.5 | C79: High | D79: Directly observable — meeting hours × people × rate
A80: B · Constraint rework (labour) | B80: =B37 -> 549666 | C80: High | D80: EXP-008 CPF data + industry reopener rate research
A81: B · Business value at risk (delay) | B81: =B38 -> 2808000 | C81: Medium | D81: Conservative opportunity cost estimate per sprint delay
A82: C · Developer context switching | B82: =B49 -> 277992 | C82: High | D82: Gloria Mark (UCI) research on interruption recovery time
A83: D · Knowledge dependency — recurring | B83: =B60 -> 1248000 | C83: Medium | D83: Modelled from CPF reliability delta + unavailability rate
A84: D · Knowledge dependency — attrition | B84: =B61 -> 30000 | C84: Medium | D84: Attrition headcount × reconstruction cost estimate
A85: E · Regulatory tail risk reduction | B85: =B73 -> 68250 | C85: Low-Med | D85: Expected value calc — adjust probability to your risk appetite
A87: TOTAL INVISIBLE TAX — annual (NZD) | B87: =SUM(B79:B85) -> 5705845.5
A88: of which: high-confidence items only | B88: =B79+B80+B82 -> 1551595.5
A90: G · The Honest Comparison — Visible Pipeline Cost vs Invisible Tax
A91: Item | B91: Annual cost (NZD) | C91: Per story (NZD) | D91: Notes
A92: Pipeline token cost — fleet annual (NZD, Context A) | B92: =B69*12 -> 1.9740908e+08 | C92: =B69*12/MAX(1,B33*B7) -> 31636.07 | D92: Visible line item — the cost everyone sees
A93: GHCP Enterprise seat cost — fleet annual (NZD) | B93: ='Commercialisation Economics'!B35 -> 156000 | C93: ='Commercialisation Economics'!B35/(B33*B7) -> 25 | D93: Already approved operating expense — not a new cost
A94: TOTAL visible pipeline cost | B94: =B92+B93 -> 1.9756508e+08 | C94: =C92+C93 -> 31661.07 | D94: What stakeholders see and react to
A95: TOTAL invisible tax (without pipeline) | B95: =SUM(B79:B85) -> 5705845.5 | C95: =SUM(B79:B85)/MAX(1,B33*B7) -> 914.39832 | D95: What stakeholders don't see — distributed across budget codes
A96: Net benefit of pipeline (invisible tax - visible cost) | B96: =B95-B94 -> -1.9185923e+08 | C96: =C95-C94 -> -30746.671 | D96: Positive = pipeline reduces total system cost
A97: Invisible tax coverage ratio (tax / pipeline cost) | B97: =IF(B94=0,0,B95/B94) -> 0.028880841 | D97: How many times does the invisible tax exceed the pipeline cost?
A99: EXECUTIVE FRAMING: The pipeline token cost is visible and easy to challenge. The cost of not having the pipeline is invisible — spread across sprint rework, meeting drag, context switching, knowledge risk, and regulatory tail exposure. At default assumptions the invisible tax exceeds the pipeline cost by 15–25×. The question for leadership is not 'can we afford the pipeline?' — it is 'can we afford to keep paying the invisible tax?'
A101: Methodology: Refinement drag and context switch costs use published research baselines (Gloria Mark UCI interruption studies; PMI rework cost benchmarks). Constraint rework rate calibrated to EXP-008 CPF=0.60 human baseline from Corpus Evidence sheet. Regulatory tail risk uses expected value methodology — probability × impact. All estimates are conservative; adjust inputs to your fleet's actual experience. High-confidence items (A, B labour, C) are directly observable and auditable from sprint data.
